nornir_paramiko/__init__.py
nornir_paramiko/exceptions.py
nornir_paramiko/plugins/__init__.py
nornir_paramiko/plugins/connections/__init__.py
nornir_paramiko/plugins/tasks/__init__.py
nornir_paramiko/plugins/tasks/paramiko_command.py
nornir_paramiko/plugins/tasks/paramiko_sftp.py
nornir_paramiko/py.typed
nornir_paramiko-0.3.0.dist-info/LICENSE
nornir_paramiko-0.3.0.dist-info/METADATA
nornir_paramiko-0.3.0.dist-info/WHEEL
nornir_paramiko-0.3.0.dist-info/entry_points.txt
nornir_paramiko-0.3.0.dist-info/RECORD
